nginx_python/__init__.py
nginx_python/cli.py
nginx_python/core.py
python-nginx/__init__.py
python-nginx/cli.py
python-nginx/core.py
python_nginx/__init__.py
python_nginx/cli.py
python_nginx/core.py
nginx_python-0.1.1.dist-info/LICENSE
nginx_python-0.1.1.dist-info/METADATA
nginx_python-0.1.1.dist-info/WHEEL
nginx_python-0.1.1.dist-info/entry_points.txt
nginx_python-0.1.1.dist-info/top_level.txt
nginx_python-0.1.1.dist-info/RECORD
