Metadata-Version: 2.1
Name: nginx_python
Version: 0.1.1
License-File: LICENSE
Requires-Dist: jinja2
Requires-Dist: requests
